easy_image_processor/__init__.py
easy_image_processor/core.py
easy_image_processor-0.1.0.dist-info/LICENSE
easy_image_processor-0.1.0.dist-info/METADATA
easy_image_processor-0.1.0.dist-info/WHEEL
easy_image_processor-0.1.0.dist-info/top_level.txt
easy_image_processor-0.1.0.dist-info/RECORD
